tahoe_idp/__init__.py
tahoe_idp/api.py
tahoe_idp/apps.py
tahoe_idp/backend.py
tahoe_idp/constants.py
tahoe_idp/helpers.py
tahoe_idp/magiclink_backends.py
tahoe_idp/magiclink_helpers.py
tahoe_idp/magiclink_utils.py
tahoe_idp/magiclink_views.py
tahoe_idp/models.py
tahoe_idp/permissions.py
tahoe_idp/receivers.py
tahoe_idp/urls.py
tahoe_idp/migrations/0001_initial.py
tahoe_idp/migrations/0002_allow_null_redirect_url.py
tahoe_idp/migrations/__init__.py
tahoe_idp/settings/__init__.py
tahoe_idp/settings/cms_production.py
tahoe_idp/settings/common_production.py
tahoe_idp/settings/lms_production.py
tahoe_idp-2.6.0.dist-info/LICENSE
tahoe_idp-2.6.0.dist-info/METADATA
tahoe_idp-2.6.0.dist-info/WHEEL
tahoe_idp-2.6.0.dist-info/entry_points.txt
tahoe_idp-2.6.0.dist-info/top_level.txt
tahoe_idp-2.6.0.dist-info/RECORD
