Metadata-Version: 2.1
Name: tahoe-idp
Version: 2.6.0
Summary: Tahoe IdP user authentication package for Tahoe.
Home-page: https://github.com/appsembler/tahoe-idp
Author: Appsembler
Author-email: ops@appsembler.com
Project-URL: Bug Tracker, https://github.com/appsembler/tahoe-idp/issues
Classifier: Development Status :: 1 - Planning
Classifier: Intended Audience :: Developers
Classifier: Operating System :: OS Independent
Classifier: License :: OSI Approved :: MIT License
Classifier: Topic :: Software Development :: Libraries :: Python Modules
Classifier: Programming Language :: Python
Classifier: Programming Language :: Python :: 3.5
Classifier: Framework :: Django
Classifier: Framework :: Django :: 2.2
Requires-Python: >=3.5
License-File: LICENSE
